{
    "boxShadow": "{{appsmith.theme.boxShadow.appBoxShadow}}",
    "borderColor": "#E0DEDE",
    "isCanvas": true,
    "iconSVG": "https://appcdn.appsmith.com/static/media/icon.02aab13974bb96ab5effaedb467a923c.svg",
    "topRow": 14,
    "type": "TABS_WIDGET",
    "animateLoading": true,
    "leftColumn": 1,
    "dynamicBindingPathList": [
        {"key": "accentColor"},
        {"key": "borderRadius"},
        {"key": "boxShadow"},
        {"key": "defaultTab"}
    ],
    "children": [
        {
            "needsErrorInfo": false,
            "tabId": "tab1",
            "boxShadow": "{{appsmith.theme.boxShadow.appBoxShadow}}",
            "mobileBottomRow": 150,
            "widgetName": "Canvas3",
            "displayName": "Canvas",
            "bottomRow": 480,
            "topRow": 0,
            "parentRowSpace": 1,
            "type": "CANVAS_WIDGET",
            "canExtend": true,
            "hideCard": true,
            "shouldScrollContents": false,
            "minHeight": 150,
            "mobileRightColumn": 143.5,
            "parentColumnSpace": 1,
            "dynamicTriggerPathList": [],
            "leftColumn": 0,
            "dynamicBindingPathList": [
                {"key": "borderRadius"},
                {"key": "boxShadow"}
            ],
            "isDisabled": false,
            "key": "bqfmp5h3vr",
            "isDeprecated": false,
            "tabName": "Table",
            "rightColumn": 143.5,
            "detachFromLayout": true,
            "dynamicHeight": "AUTO_HEIGHT",
            "widgetId": "dmdq9jfaqf",
            "minWidth": 450,
            "isVisible": true,
            "version": 1,
            "parentId": "1y3lr0lu2a",
            "renderMode": "CANVAS",
            "isLoading": false,
            "mobileTopRow": 0,
            "responsiveBehavior": "fill",
            "borderRadius": "{{appsmith.theme.borderRadius.appBorderRadius}}",
            "mobileLeftColumn": 0,
            "maxDynamicHeight": 9000,
            "minDynamicHeight": 4,
            "flexLayers": []
        },
        {
            "needsErrorInfo": false,
            "tabId": "tab2",
            "boxShadow": "{{appsmith.theme.boxShadow.appBoxShadow}}",
            "mobileBottomRow": 150,
            "widgetName": "Canvas4",
            "displayName": "Canvas",
            "bottomRow": 480,
            "topRow": 0,
            "parentRowSpace": 1,
            "type": "CANVAS_WIDGET",
            "canExtend": true,
            "hideCard": true,
            "shouldScrollContents": false,
            "minHeight": 150,
            "mobileRightColumn": 143.5,
            "parentColumnSpace": 1,
            "dynamicTriggerPathList": [],
            "leftColumn": 0,
            "dynamicBindingPathList": [
                {"key": "borderRadius"},
                {"key": "boxShadow"}
            ],
            "isDisabled": false,
            "key": "bqfmp5h3vr",
            "isDeprecated": false,
            "tabName": "Detail",
            "rightColumn": 143.5,
            "detachFromLayout": true,
            "dynamicHeight": "AUTO_HEIGHT",
            "widgetId": "rbt7d1ayzj",
            "minWidth": 450,
            "isVisible": true,
            "version": 1,
            "parentId": "1y3lr0lu2a",
            "renderMode": "CANVAS",
            "isLoading": false,
            "mobileTopRow": 0,
            "responsiveBehavior": "fill",
            "borderRadius": "{{appsmith.theme.borderRadius.appBorderRadius}}",
            "mobileLeftColumn": 0,
            "maxDynamicHeight": 9000,
            "minDynamicHeight": 4,
            "flexLayers": []
        },
        {
            "needsErrorInfo": false,
            "tabId": "tab71oj68i5qy",
            "boxShadow": "{{appsmith.theme.boxShadow.appBoxShadow}}",
            "mobileBottomRow": 431,
            "widgetName": "Canvas5",
            "displayName": "Canvas",
            "topRow": 1,
            "bottomRow": 480,
            "parentRowSpace": 1,
            "type": "CANVAS_WIDGET",
            "canExtend": false,
            "hideCard": true,
            "minHeight": 430,
            "mobileRightColumn": 1130.0625,
            "parentColumnSpace": 1,
            "dynamicTriggerPathList": [],
            "leftColumn": 0,
            "dynamicBindingPathList": [
                {"key": "borderRadius"},
                {"key": "boxShadow"}
            ],
            "key": "bqfmp5h3vr",
            "isDeprecated": false,
            "tabName": "List",
            "rightColumn": 1130.0625,
            "detachFromLayout": true,
            "dynamicHeight": "AUTO_HEIGHT",
            "widgetId": "b32ol9fw54",
            "containerStyle": "none",
            "minWidth": 450,
            "isVisible": true,
            "version": 1,
            "parentId": "1y3lr0lu2a",
            "renderMode": "CANVAS",
            "isLoading": false,
            "mobileTopRow": 1,
            "responsiveBehavior": "fill",
            "borderRadius": "{{appsmith.theme.borderRadius.appBorderRadius}}",
            "mobileLeftColumn": 0,
            "maxDynamicHeight": 9000,
            "minDynamicHeight": 4,
            "flexLayers": []
        }
    ],
    "flexVerticalAlignment": "stretch",
    "dynamicHeight": "AUTO_HEIGHT",
    "accentColor": "{{appsmith.theme.colors.primaryColor}}",
    "shouldShowTabs": true,
    "isVisible": true,
    "version": 3,
    "tags": ["Layout"],
    "isLoading": false,
    "borderRadius": "{{appsmith.theme.borderRadius.appBorderRadius}}",
    "originalBottomRow": 66,
    "needsErrorInfo": false,
    "mobileBottomRow": 63,
    "widgetName": "Tabs1",
    "dynamicPropertyPathList": [{"key": "onTabSelected"}],
    "displayName": "Tabs",
    "bottomRow": 66,
    "parentRowSpace": 10,
    "hideCard": false,
    "shouldScrollContents": true,
    "mobileRightColumn": 8,
    "parentColumnSpace": 17.9375,
    "dynamicTriggerPathList": [{"key": "onTabSelected"}],
    "borderWidth": 1,
    "key": "0sjop7ao5q",
    "backgroundColor": "#FFFFFF",
    "isDeprecated": false,
    "rightColumn": 64,
    "thumbnailSVG": "https://appcdn.appsmith.com/static/media/thumbnail.902d280515fd575657e8ccf99545112b.svg",
    "widgetId": "1y3lr0lu2a",
    "defaultTab": "{{JSObject1.defaultTab}}",
    "onTabSelected": "{{JSObject1.defaultTab = Tabs1.selectedTab}}",
    "minWidth": 450,
    "tabsObj": {
        "tab1": {
            "widgetId": "dmdq9jfaqf",
            "positioning": "vertical",
            "index": 0,
            "label": "Table",
            "id": "tab1",
            "isVisible": true
        },
        "tab2": {
            "widgetId": "rbt7d1ayzj",
            "positioning": "vertical",
            "index": 1,
            "label": "Detail",
            "id": "tab2",
            "isVisible": true
        },
        "tab71oj68i5qy": {
            "widgetId": "b32ol9fw54",
            "index": 2,
            "id": "tab71oj68i5qy",
            "label": "List",
            "isVisible": true
        }
    },
    "parentId": "0",
    "renderMode": "CANVAS",
    "mobileTopRow": 48,
    "responsiveBehavior": "fill",
    "originalTopRow": 14,
    "mobileLeftColumn": 0,
    "maxDynamicHeight": 9000,
    "minDynamicHeight": 15
}